pymf6/__init__.py
pymf6/_version.py
pymf6/api.py
pymf6/datastructures.py
pymf6/main.py
pymf6/mf6.py
pymf6/resources/mf6_var_names/input_vars/6.4.1/exg/gwfgwf.json
pymf6/resources/mf6_var_names/input_vars/6.4.1/exg/gwfgwt.json
pymf6/resources/mf6_var_names/input_vars/6.4.1/exg/gwtgwt.json
pymf6/resources/mf6_var_names/input_vars/6.4.1/gwf/api.json
pymf6/resources/mf6_var_names/input_vars/6.4.1/gwf/buy.json
pymf6/resources/mf6_var_names/input_vars/6.4.1/gwf/chd.json
pymf6/resources/mf6_var_names/input_vars/6.4.1/gwf/csub.json
pymf6/resources/mf6_var_names/input_vars/6.4.1/gwf/dis.json
pymf6/resources/mf6_var_names/input_vars/6.4.1/gwf/disu.json
pymf6/resources/mf6_var_names/input_vars/6.4.1/gwf/disv.json
pymf6/resources/mf6_var_names/input_vars/6.4.1/gwf/drn.json
pymf6/resources/mf6_var_names/input_vars/6.4.1/gwf/evt.json
pymf6/resources/mf6_var_names/input_vars/6.4.1/gwf/evta.json
pymf6/resources/mf6_var_names/input_vars/6.4.1/gwf/ghb.json
pymf6/resources/mf6_var_names/input_vars/6.4.1/gwf/gnc.json
pymf6/resources/mf6_var_names/input_vars/6.4.1/gwf/hfb.json
pymf6/resources/mf6_var_names/input_vars/6.4.1/gwf/ic.json
pymf6/resources/mf6_var_names/input_vars/6.4.1/gwf/lak.json
pymf6/resources/mf6_var_names/input_vars/6.4.1/gwf/maw.json
pymf6/resources/mf6_var_names/input_vars/6.4.1/gwf/mvr.json
pymf6/resources/mf6_var_names/input_vars/6.4.1/gwf/nam.json
pymf6/resources/mf6_var_names/input_vars/6.4.1/gwf/npf.json
pymf6/resources/mf6_var_names/input_vars/6.4.1/gwf/oc.json
pymf6/resources/mf6_var_names/input_vars/6.4.1/gwf/rch.json
pymf6/resources/mf6_var_names/input_vars/6.4.1/gwf/rcha.json
pymf6/resources/mf6_var_names/input_vars/6.4.1/gwf/riv.json
pymf6/resources/mf6_var_names/input_vars/6.4.1/gwf/sfr.json
pymf6/resources/mf6_var_names/input_vars/6.4.1/gwf/sto.json
pymf6/resources/mf6_var_names/input_vars/6.4.1/gwf/uzf.json
pymf6/resources/mf6_var_names/input_vars/6.4.1/gwf/vsc.json
pymf6/resources/mf6_var_names/input_vars/6.4.1/gwf/wel.json
pymf6-1.2.0.dist-info/LICENSE
pymf6-1.2.0.dist-info/METADATA
pymf6-1.2.0.dist-info/WHEEL
pymf6-1.2.0.dist-info/entry_points.txt
pymf6-1.2.0.dist-info/top_level.txt
pymf6-1.2.0.dist-info/RECORD
