Metadata-Version: 2.1
Name: pymf6
Version: 1.2.0
Summary: High-level Python Wrapper for MODFLOW 6
License: MIT License
Project-URL: homepage, https://github.com/hydrocomputing/pymf6
Project-URL: documentation, https://pymf6.readthedocs.io/en/latest/index.html
Project-URL: repository, https://github.com/hydrocomputing/pymf6
Keywords: packaging,example
Classifier: Development Status :: 3 - Alpha
Classifier: License :: OSI Approved :: MIT License
Classifier: Programming Language :: Python :: 3
Classifier: Environment :: Console
Classifier: Framework :: Jupyter :: JupyterLab
Classifier: Intended Audience :: Developers
Classifier: Intended Audience :: Science/Research
Classifier: Operating System :: Microsoft :: Windows
Classifier: Operating System :: POSIX
Classifier: Operating System :: MacOS :: MacOS X
Classifier: Programming Language :: Python :: Implementation :: CPython
Classifier: Intended Audience :: Science/Research
Classifier: Topic :: Scientific/Engineering :: Hydrology
Requires-Python: >=3.8
License-File: LICENSE
Requires-Dist: modflowapi
